antipattern_mitigation/__init__.py
antipattern_mitigation/__main__.py
antipattern_mitigation/service/__init__.py
antipattern_mitigation/service/_service.py
antipattern_mitigation-0.1.0.dist-info/WHEEL
antipattern_mitigation-0.1.0.dist-info/METADATA
antipattern_mitigation-0.1.0.dist-info/RECORD
