Metadata-Version: 2.1
Name: antipattern-mitigation
Version: 0.1.0
Summary: 
Author: ulfet
Author-email: ulfet.rwth@gmail.com
Requires-Python: >=3.8,<4.0
Classifier: Programming Language :: Python :: 3
Classifier: Programming Language :: Python :: 3.8
Classifier: Programming Language :: Python :: 3.9
Requires-Dist: fastapi (>=0.63.0,<0.64.0)
Requires-Dist: uvicorn (>=0.13.2,<0.14.0)
